wikihowapi_pk/__init__.py
wikihowapi_pk/exceptions.py
wikihowapi_pk-0.0.5.dist-info/LICENSE
wikihowapi_pk-0.0.5.dist-info/METADATA
wikihowapi_pk-0.0.5.dist-info/WHEEL
wikihowapi_pk-0.0.5.dist-info/top_level.txt
wikihowapi_pk-0.0.5.dist-info/RECORD
