Metadata-Version: 2.1
Name: wikihowapi-pk
Version: 0.0.5
Summary: API to extract more data from wikiHow
Home-page: https://github.com/p1k0pan/AdaptiveStoryFinder.git
Author: p1k0pan
Author-email: pan.jingheng1998@gmail.com
License: MIT
Classifier: Intended Audience :: Science/Research
Classifier: License :: OSI Approved :: MIT License
Classifier: Operating System :: OS Independent
Classifier: Programming Language :: Python :: 3
Requires-Python: >=3.6
License-File: LICENSE
Requires-Dist: bs4
Requires-Dist: tqdm
